{
    "name": "Bezoekers: ",
    "number": "500.000",
    "children": [
        {
            "name": "Toeschouwers: ",
            "number": "100.000",
            "children": [
                {
                    "name": "Per avond: ",
                    "number": "10.000"
                }
            ]
        },
        {
            "name": "Spelers: ",
            "number": "4.000",
            "children": [
                {
                    "name": "Per avond: ",
                    "number": "400"
                }
            ]
        }
    ]
}